tensorflow_hub/__init__.py
tensorflow_hub/compressed_module_resolver.py
tensorflow_hub/config.py
tensorflow_hub/file_utils.py
tensorflow_hub/keras_layer.py
tensorflow_hub/module_v2.py
tensorflow_hub/registry.py
tensorflow_hub/resolver.py
tensorflow_hub/tf_utils.py
tensorflow_hub/uncompressed_module_resolver.py
tensorflow_hub/version.py
tf_hub_nightly-0.17.0.dev202509050305.dist-info/METADATA
tf_hub_nightly-0.17.0.dev202509050305.dist-info/WHEEL
tf_hub_nightly-0.17.0.dev202509050305.dist-info/top_level.txt
tf_hub_nightly-0.17.0.dev202509050305.dist-info/RECORD
