Metadata-Version: 2.4
Name: tf-hub-nightly
Version: 0.17.0.dev202509050305
Summary: TensorFlow Hub is a library to foster the publication, discovery, and consumption of reusable parts of machine learning models.
Home-page: https://github.com/tensorflow/hub
Author: Google LLC
Author-email: packages@tensorflow.org
License: Apache 2.0
Keywords: tensorflow machine learning share module subgraph component hub embedding retraining transfer
Platform: UNKNOWN
Classifier: Development Status :: 4 - Beta
Classifier: Intended Audience :: Developers
Classifier: Intended Audience :: Education
Classifier: Intended Audience :: Science/Research
Classifier: License :: OSI Approved :: Apache Software License
Classifier: Programming Language :: Python :: 3
Classifier: Programming Language :: Python :: 3.9
Classifier: Programming Language :: Python :: 3.10
Classifier: Programming Language :: Python :: 3 :: Only
Classifier: Topic :: Scientific/Engineering
Classifier: Topic :: Scientific/Engineering :: Mathematics
Classifier: Topic :: Scientific/Engineering :: Artificial Intelligence
Classifier: Topic :: Software Development
Classifier: Topic :: Software Development :: Libraries
Classifier: Topic :: Software Development :: Libraries :: Python Modules
Requires-Dist: numpy>=1.12.0
Requires-Dist: protobuf>=3.19.6
Requires-Dist: tf-keras-nightly
Dynamic: author
Dynamic: author-email
Dynamic: classifier
Dynamic: home-page
Dynamic: keywords
Dynamic: license
Dynamic: requires-dist
Dynamic: summary
